{
    "avatar": "/resume/data/avatar.jpg",
    "background_image": "https://9to5mac.files.wordpress.com/2014/08/yosemite-3.jpg?w=1200&h=&crop=1",
    "basicinfo": {
        "name": "熊都",
        "description": "春风若有怜花意，可否许我再少年",
        "school": "河南农业大学",
        "profession": "计算机科学与技术",
        "sex": "男",
        "education" : "硕士",
        "workage": "2024届毕业",
        "phone": "15236447077",
        "email": "1822649761@qq.com"
    },
    "social":[
        {
            "type": "github",
            "link": "https://github.com/LoveCode77",
            "icon": ""
        },
        {
            "type": "weibo",
            "link": "http://weibo.com",
            "icon": ""
        },
        {
            "type": "linkedin",
            "link": "https://www.linkedin.com",
            "icon": ""
        },
        {
            "type": "twitter",
            "link": "https://twitter.com",
            "icon": ""
        },
        {
            "type": "home",
            "link": "https://github.com/LoveCode77",
            "icon": ""
        }
    ],
    "Awards": [
        {
            "name": "2021年河南农业大学一等奖学金"
        },
        {
            "name": "2022年河南农业大学二等奖学金"
        },
        {
            "name": "2023年河南农业大学二等奖学金"
        },
        {
            "name": "蓝桥杯程序竞赛二等奖"
        },
        {
            "name": "校学生会宣传部先进个人"
        }
    ],
    "socialExperiences": [
        {
            "name": "生活委员",
            "name_link": "",
            "description": "在2017年-2021年本科学习期间担任生活委员。生活委员是班级委员会委员之一。在校期间，负责学生生活相关工作并协助班长和团支书管理班级事务。如负责保存和使用班费，并定期向班委会和全班同学公布；关心同学们的日常生活，在流感易发季节采取预防措施；定期举行宿舍负责人会议，以确保宿舍的纪律和清洁以及学生的身体健康；注意学生的健康饮食，并不时提醒他们保持合理饮食。"
        },
        {
            "name": "校学生会宣传部副部长",
            "name_link": "",
            "description": "在2018年到2020年间担任学校宣传部副部长职务，在此期间负责宣传部的日常工作，如微信端、QQ端和微博端的文案审核和编写，同时掌握了PS和PR等技术进行活动海报制作和视频剪辑。负责了”金秋书画展”、“校元旦晚会”和“校园歌手大赛”等活动的开展与前后期宣传工作。"
        }
    ],
    "InternExperiences": [
        {
            "name": "河南驭数软件科技有限公司",
            "name_link": "",
            "title": "Java开发工程师",
            "icon": "",
            "description": "项目描述：编程枪代码生成器-后台管理系统是一个基于前后端分离的后台管理系统。主要技术为：SpringBoot+Vue+Mybatis+Mysql+Redis+Activiti+SpringValidation+Shrio职责与相关技术描述：为后台管理系统生成的模板代码增加对数据库增删改查、导入导出操作和后端数据校验。为后台管理系统整合阿里云短信服务和邮件服务，使用Shrio控制角色权限到按钮级别，整合工作流Activiti实现流程审批。",
            "time": "2021.05 - 2021.09",
            "location": "河南 郑州"
        }
    ],
    "ProjectExperience": [
        {
            "name": "小麦生长数字孪生系统",
            "name_link": "",
            "title": "项目负责人",
            "icon": "",
            "description": "项目描述：使用技术nginx+springboot+tomcat+mybatis-plus+mysql+redis职责与相关技术描述：使用传感器基于RS485搭建田间数据采集总线网络，基于springboot搭建服务器实现数据自动获取，基于MySQL进行数据存储，基于Nginx搭建流服务器。基于Mars3D和Three.js搭建前端数字孪生系统进行数据可视化展示。",
            "time": "2022.07 - 2023.09",
            "location": ""
        },
        {
            "name": "小麦智慧大数据平台",
            "name_link": "",
            "title": "项目后端开发",
            "icon": "",
            "description": "项目描述：主要使用HTML5+Echarts+SpringBoot开发，子项目使用SpingCloud微服务架构实现数据交互，数据存储使用Mysql集群。子项目分为系统数据大屏、小麦产量预测、小麦灾害预测预警、物联网站点实时监控。职责与相关技术描述：使用Mysql集群对物联网数据、设备信息和多个设备的采集历史记录等数据，使用Ridis进行数据缓存，存放数据大屏的实时更新数据。使用Mybatis对数据库进行读写操作，将产量预测数学模型和灾害预测数学模型程序化，使用物联网数据进行产量预测和灾害预警。使用Mars3D可视化框架对小麦产量数据，灾害数据、物联网数据通过地图3D化、柱状图、折线图进行展示，并接入物联网实时视频数据并实现摄像头操作。",
            "time": "2021.10 - 2022.12",
            "location": ""
        },
        {
            "name": "城镇智慧公交系统",
            "name_link": "",
            "title": "Java开发工程师",
            "icon": "",
            "description": "项目描述：基于前后端分离的城镇公交调度项目，主要功能是实现对公交车的管理和调度。分为车辆管理、车队管理、线路管理、司机管理、信息发布等模块。使用spring+springmvc+mybatis+mysql进行后端开发，vue+element-ui进行前端搭建。职责与相关技术描述：通过PowerDesigner设计并建立Mysql数据库，负责线路管理模块业务代码编写，在前端利用高德地图Api实现公交线路可视化展示。",
            "time": "2020.10 - 2021.04",
            "location": ""
        },
        {
            "name": "河南省农作物面积遥感测量作物分类",
            "name_link": "",
            "title": "项目主要参与人",
            "icon": "",
            "description": "项目描述：由河南省统计局和河南农业大学信管学院合作的河南省农作物面积遥感测量项目，其中作物分类项目需要通过深度学习与机器学习对遥感影像中的九大地物进行识别，通过Arcgis软件对矢量数据进行辅助标注，用于样方和实际调查，最终实现对河南省夏粮与秋粮作物面积的统计。职责与相关技术描述：通过一站式遥感大数据并行处理平台下载哨兵、高分等影像数据，对影像数据进行预处理处理，采用Arcgis软件对影像数据操作，修改并填写矢量数据,利用Java处理excel和开发小工具提高工作效率。",
            "time": "2021.10 - 2023.09",
            "location": ""
        },
        {
            "name": "更多",
            "name_link": "https://github.com/LoveCode77",
            "title": "",
            "icon": "",
            "description": "",
            "time": "",
            "location": ""
        }
    ]
}
